{
  "parent": "minecraft:recipes/root",
  "criteria": {
    "has_patina": {
      "trigger": "minecraft:inventory_changed",
      "conditions": {
        "items": [
          {
            "items": "additionaladditions:copper_patina"
          }
        ]
      }
    },
    "has_the_recipe": {
      "trigger": "minecraft:recipe_unlocked",
      "conditions": {
        "recipe": "additionaladditions:copper_patina/patina_block"
      }
    }
  },
  "requirements": [
    [
      "has_patina",
      "has_the_recipe"
    ]
  ],
  "rewards": {
    "recipes": [
      "additionaladditions:copper_patina/patina_block"
    ]
  }
}